{"$schema": "https://developer.microsoft.com/json-schemas/fabric/item/report/definition/visualContainer/2.10.0/schema.json", "name": "69be66dcf86f40e294bf", "position": {"x": 640, "y": 198, "z": 7, "height": 250, "width": 640, "tabOrder": 7}, "visual": {"visualType": "clusteredBarChart", "query": {"queryState": {"Category": {"projections": [{"field": {"Column": {"Expression": {"SourceRef": {"Entity": "Service"}}, "Property": "store_name"}}, "queryRef": "Service.store_name", "nativeQueryRef": "store_name", "active": true}]}, "Y": {"projections": [{"field": {"Measure": {"Expression": {"SourceRef": {"Entity": "Service"}}, "Property": "Total Revenue"}}, "queryRef": "Service.Total Revenue", "nativeQueryRef": "Total Revenue"}]}}, "sortDefinition": {"sort": [{"field": {"Measure": {"Expression": {"SourceRef": {"Entity": "Service"}}, "Property": "Total Revenue"}}, "direction": "Descending"}], "isDefaultSort": true}}, "drillFilterOtherVisuals": true, "visualContainerObjects": {"title": [{"properties": {"text": {"expr": {"Literal": {"Value": "'Revenue by Store'"}}}}}]}}}